odoo/addons/stock_release_channel_process_end_time/README.rst
odoo/addons/stock_release_channel_process_end_time/__init__.py
odoo/addons/stock_release_channel_process_end_time/__manifest__.py
odoo/addons/stock_release_channel_process_end_time/utils.py
odoo/addons/stock_release_channel_process_end_time/i18n/es.po
odoo/addons/stock_release_channel_process_end_time/i18n/fr.po
odoo/addons/stock_release_channel_process_end_time/i18n/it.po
odoo/addons/stock_release_channel_process_end_time/i18n/stock_release_channel_process_end_time.pot
odoo/addons/stock_release_channel_process_end_time/models/__init__.py
odoo/addons/stock_release_channel_process_end_time/models/res_config_settings.py
odoo/addons/stock_release_channel_process_end_time/models/stock_move.py
odoo/addons/stock_release_channel_process_end_time/models/stock_picking.py
odoo/addons/stock_release_channel_process_end_time/models/stock_release_channel.py
odoo/addons/stock_release_channel_process_end_time/readme/CONTRIBUTORS.md
odoo/addons/stock_release_channel_process_end_time/readme/DESCRIPTION.md
odoo/addons/stock_release_channel_process_end_time/readme/ROADMAP.md
odoo/addons/stock_release_channel_process_end_time/readme/USAGE.md
odoo/addons/stock_release_channel_process_end_time/static/description/icon.png
odoo/addons/stock_release_channel_process_end_time/static/description/index.html
odoo/addons/stock_release_channel_process_end_time/tests/__init__.py
odoo/addons/stock_release_channel_process_end_time/tests/test_release_end_date.py
odoo/addons/stock_release_channel_process_end_time/views/res_config_settings.xml
odoo/addons/stock_release_channel_process_end_time/views/stock_release_channel.xml
odoo_addon_stock_release_channel_process_end_time-18.0.1.0.1.dist-info/METADATA
odoo_addon_stock_release_channel_process_end_time-18.0.1.0.1.dist-info/WHEEL
odoo_addon_stock_release_channel_process_end_time-18.0.1.0.1.dist-info/top_level.txt
odoo_addon_stock_release_channel_process_end_time-18.0.1.0.1.dist-info/RECORD
