Metadata-Version: 2.1
Name: odoo-addon-stock_release_channel_process_end_time
Version: 18.0.1.0.1
Requires-Python: >=3.10
Requires-Dist: odoo-addon-partner_tz==18.0.*
Requires-Dist: odoo-addon-stock_available_to_promise_release==18.0.*
Requires-Dist: odoo-addon-stock_release_channel==18.0.*
Requires-Dist: odoo==18.0.*
Summary: Allows to define an end date (and time) on a release channel and propagate it to the concerned pickings
Home-page: https://github.com/OCA/stock-logistics-release-channel
License: AGPL-3
Author: ACSONE SA/NV,BCIM,Odoo Community Association (OCA)
Author-email: support@odoo-community.org
Classifier: Programming Language :: Python
Classifier: Framework :: Odoo
Classifier: Framework :: Odoo :: 18.0
Classifier: License :: OSI Approved :: GNU Affero General Public License v3
